teamoflow/__init__.py
teamoflow/mf/__init__.py
teamoflow/mf/embedding_graphs.py
teamoflow/mf/initializer_graphs.py
teamoflow/mf/input_utils.py
teamoflow/mf/loss_graphs.py
teamoflow/mf/matrix_factorization.py
teamoflow/mf/predict_graphs.py
teamoflow/mf/utils.py
teamoflow/nn/__init__.py
teamoflow/nn/user_tower.py
teamoflow-0.0.1.dist-info/LICENSE
teamoflow-0.0.1.dist-info/METADATA
teamoflow-0.0.1.dist-info/WHEEL
teamoflow-0.0.1.dist-info/top_level.txt
teamoflow-0.0.1.dist-info/RECORD
