Metadata-Version: 2.1
Name: teamoflow
Version: 0.0.1
Summary: A TensorFlow 2.X-based matrix factorization framework, particularly for the purpose of query (user)-value (item) matching.
Author-email: andrew_jy <andrewjych@gmail.com>
Project-URL: Homepage, https://github.com/GitHubOfAndrew/TeAMOFlow
Project-URL: Bug Tracker, https://github.com/GitHubOfAndrew/TeAMOFlow/issues
Classifier: Programming Language :: Python :: 3
Classifier: License :: OSI Approved :: Apache Software License
Classifier: Operating System :: OS Independent
Requires-Python: >=3.7
License-File: LICENSE
